setup.py
sweetcaptcha/__init__.py
sweetcaptcha/flaskdemo.py
sweetcaptcha/sweetcaptchawt.py
sweetcaptcha.egg-info/PKG-INFO
sweetcaptcha.egg-info/SOURCES.txt
sweetcaptcha.egg-info/dependency_links.txt
sweetcaptcha.egg-info/top_level.txt