Metadata-Version: 1.1
Name: sweetcaptcha
Version: 0.1
Summary: API for easy integration of sweetcaptchas (http://sweetcaptcha.com/)
Home-page: https://pypi.python.org/pypi/sweetcaptcha
Author: Jaime Wyant
Author-email: programmer.py@gmail.com
License: BSD
Keywords: sweetcaptcha captcha
Platform: UNKNOWN
Classifier: Development Status :: 4 - Beta
Classifier: Programming Language :: Python :: 2
Classifier: Intended Audience :: Developers
Classifier: Operating System :: OS Independent
Classifier: Topic :: Software Development :: Widget Sets
Classifier: License :: OSI Approved :: BSD License
